zip2kafka/__init__.py
zip2kafka/main.py
zip2kafka-0.1.0.dist-info/entry_points.txt
zip2kafka-0.1.0.dist-info/WHEEL
zip2kafka-0.1.0.dist-info/METADATA
zip2kafka-0.1.0.dist-info/RECORD
